hk_ai_common/__init__.py
hk_ai_common/date.py
hk_ai_common/logger.py
hk_ai_common/utils.py
hk_ai_common/http/__init__.py
hk_ai_common/http/contextvar.py
hk_ai_common/http/exception.py
hk_ai_common/http/request.py
hk_ai_common/http/timer.py
hk_ai_common-1.0.3.dist-info/LICENSE.txt
hk_ai_common-1.0.3.dist-info/METADATA
hk_ai_common-1.0.3.dist-info/WHEEL
hk_ai_common-1.0.3.dist-info/top_level.txt
hk_ai_common-1.0.3.dist-info/RECORD
